odoo/addons/hr_holidays_leave_request_wizard/README.rst
odoo/addons/hr_holidays_leave_request_wizard/__init__.py
odoo/addons/hr_holidays_leave_request_wizard/__manifest__.py
odoo/addons/hr_holidays_leave_request_wizard/i18n/fr.po
odoo/addons/hr_holidays_leave_request_wizard/i18n/hr_holidays_leave_request_wizard.pot
odoo/addons/hr_holidays_leave_request_wizard/i18n/it.po
odoo/addons/hr_holidays_leave_request_wizard/models/__init__.py
odoo/addons/hr_holidays_leave_request_wizard/models/hr_leave.py
odoo/addons/hr_holidays_leave_request_wizard/readme/CONTRIBUTORS.rst
odoo/addons/hr_holidays_leave_request_wizard/readme/DESCRIPTION.rst
odoo/addons/hr_holidays_leave_request_wizard/readme/ROADMAP.rst
odoo/addons/hr_holidays_leave_request_wizard/readme/USAGE.rst
odoo/addons/hr_holidays_leave_request_wizard/static/description/icon.png
odoo/addons/hr_holidays_leave_request_wizard/static/description/index.html
odoo/addons/hr_holidays_leave_request_wizard/tests/__init__.py
odoo/addons/hr_holidays_leave_request_wizard/tests/test_hr_holidays_leave_request_wizard.py
odoo/addons/hr_holidays_leave_request_wizard/views/hr_leave.xml
odoo/addons/hr_holidays_leave_request_wizard/wizards/__init__.py
odoo/addons/hr_holidays_leave_request_wizard/wizards/hr_leave_wizard.py
odoo/addons/hr_holidays_leave_request_wizard/wizards/hr_leave_wizard.xml
odoo12_addon_hr_holidays_leave_request_wizard-12.0.1.0.0.99.dev11.dist-info/METADATA
odoo12_addon_hr_holidays_leave_request_wizard-12.0.1.0.0.99.dev11.dist-info/WHEEL
odoo12_addon_hr_holidays_leave_request_wizard-12.0.1.0.0.99.dev11.dist-info/top_level.txt
odoo12_addon_hr_holidays_leave_request_wizard-12.0.1.0.0.99.dev11.dist-info/RECORD
